metapensiero/sphinx/d2/__init__.py
metapensiero_sphinx_d2-0.10.dist-info/METADATA
metapensiero_sphinx_d2-0.10.dist-info/WHEEL
metapensiero_sphinx_d2-0.10.dist-info/entry_points.txt
metapensiero_sphinx_d2-0.10.dist-info/RECORD
