Metadata-Version: 2.1
Name: metapensiero.sphinx.d2
Version: 0.10
Summary: Sphinx d2lang extension
Author-Email: Lele Gaifax <lele@metapensiero.it>
License: GPL-3.0-or-later
Classifier: Development Status :: 3 - Alpha
Classifier: Programming Language :: Python
Classifier: Programming Language :: Python :: 3
Classifier: Intended Audience :: Developers
Classifier: License :: OSI Approved :: GNU General Public License v3 or later (GPLv3+)
Classifier: Topic :: Utilities
Classifier: Framework :: Sphinx :: Extension
Project-URL: Changelog, https://gitlab.com/metapensiero/metapensiero.sphinx.d2/-/blob/master/CHANGES.rst
Project-URL: Source, https://gitlab.com/metapensiero/metapensiero.sphinx.d2
Requires-Python: >=3.9
Requires-Dist: sphinx
Provides-Extra: dev
Requires-Dist: build; extra == "dev"
Requires-Dist: bump-my-version; extra == "dev"
Requires-Dist: tomli; extra == "dev"
Requires-Dist: twine; extra == "dev"
